digi/__init__.py
digi/xbee/__init__.py
digi/xbee/devices.py
digi/xbee/exception.py
digi/xbee/io.py
digi/xbee/reader.py
digi/xbee/xbee_serial.py
digi/xbee/models/__init__.py
digi/xbee/models/accesspoint.py
digi/xbee/models/address.py
digi/xbee/models/atcomm.py
digi/xbee/models/hw.py
digi/xbee/models/message.py
digi/xbee/models/mode.py
digi/xbee/models/options.py
digi/xbee/models/protocol.py
digi/xbee/models/status.py
digi/xbee/packets/__init__.py
digi/xbee/packets/aft.py
digi/xbee/packets/base.py
digi/xbee/packets/cellular.py
digi/xbee/packets/common.py
digi/xbee/packets/devicecloud.py
digi/xbee/packets/factory.py
digi/xbee/packets/network.py
digi/xbee/packets/raw.py
digi/xbee/packets/wifi.py
digi/xbee/util/__init__.py
digi/xbee/util/utils.py
ngcp_xbee-1.1.dist-info/LICENSE.txt
ngcp_xbee-1.1.dist-info/METADATA
ngcp_xbee-1.1.dist-info/WHEEL
ngcp_xbee-1.1.dist-info/top_level.txt
ngcp_xbee-1.1.dist-info/RECORD
