Metadata-Version: 2.1
Name: ngcp-xbee
Version: 1.1
Summary: Digi XBee Python library, compatible with Python 2
Home-page: https://github.com/tianatonnu/python-xbee.git
Author: Tiana Ton Nu, Digi International Inc.
Author-email: tianattonnu@gmail.com, tech.support@digi.com
License: Mozilla Public License 2.0 (MPL 2.0)
Keywords: xbee,IOT,wireless,radio frequency
Platform: UNKNOWN
Classifier: Development Status :: 5 - Production/Stable
Classifier: Intended Audience :: Developers
Classifier: Intended Audience :: Telecommunications Industry
Classifier: Intended Audience :: End Users/Desktop
Classifier: Topic :: Software Development :: Libraries
Classifier: Topic :: Home Automation
Classifier: Topic :: Games/Entertainment
Classifier: License :: OSI Approved :: Mozilla Public License 2.0 (MPL 2.0)
Classifier: Programming Language :: Python :: 2
Classifier: Operating System :: OS Independent
Requires-Python: >=2
Requires-Dist: pyserial (>=3)
Requires-Dist: ipaddress (>=1)
